setup.cfg
setup.py
nodezator_plus/__init__.py
nodezator_plus/__main__.py
nodezator_plus/anim.mp4
nodezator_plus/anim.py
nodezator_plus/cli.py
nodezator_plus/double_translation.py
nodezator_plus/menu1.py
nodezator_plus/translate.py
nodezator_plus.egg-info/PKG-INFO
nodezator_plus.egg-info/SOURCES.txt
nodezator_plus.egg-info/dependency_links.txt
nodezator_plus.egg-info/not-zip-safe
nodezator_plus.egg-info/requires.txt
nodezator_plus.egg-info/top_level.txt
nodezator_plus/ru/dialogs_map.pyl
nodezator_plus/ru/status_messages_map.pyl
nodezator_plus/ru/translations_map.pyl